satellighte/.config.yaml
satellighte/__about__.py
satellighte/__init__.py
satellighte/core.py
satellighte/module.py
satellighte/utils.py
satellighte/version.py
satellighte/api/__init__.py
satellighte/archs/__init__.py
satellighte/archs/coatnet/__init__.py
satellighte/archs/coatnet/module.py
satellighte/archs/coatnet/blocks/__init__.py
satellighte/archs/coatnet/blocks/coatnet.py
satellighte/archs/coatnet/blocks/layers.py
satellighte/archs/efficientnet/__init__.py
satellighte/archs/efficientnet/module.py
satellighte/archs/efficientnet/blocks/__init__.py
satellighte/archs/efficientnet/blocks/efficientnet.py
satellighte/archs/efficientnet/blocks/layers.py
satellighte/archs/mobilenetv2/__init__.py
satellighte/archs/mobilenetv2/module.py
satellighte/archs/mobilenetv2/blocks/__init__.py
satellighte/archs/mobilenetv2/blocks/layers.py
satellighte/archs/mobilenetv2/blocks/mobilenetv2.py
satellighte/archs/resnet/__init__.py
satellighte/archs/resnet/module.py
satellighte/archs/resnet/blocks/__init__.py
satellighte/archs/resnet/blocks/layers.py
satellighte/archs/resnet/blocks/resnet.py
satellighte/datasets/__init__.py
satellighte/datasets/base.py
satellighte/datasets/eurosat.py
satellighte/datasets/resisc45.py
satellighte/models/.gitkeep
satellighte/models/efficientnet_b0_eurosat/.gitkeep
satellighte/models/efficientnet_b0_eurosat/v0/.gitkeep
satellighte/models/mobilenetv2_default_eurosat/.gitkeep
satellighte/models/mobilenetv2_default_eurosat/v0/.gitkeep
satellighte/models/mobilenetv2_default_eurosat/v1/.gitkeep
scripts/__init__.py
scripts/release.py
satellighte-0.2.5.dist-info/LICENSE
satellighte-0.2.5.dist-info/METADATA
satellighte-0.2.5.dist-info/WHEEL
satellighte-0.2.5.dist-info/top_level.txt
satellighte-0.2.5.dist-info/RECORD
