Metadata-Version: 2.1
Name: satellighte
Version: 0.2.5
Summary: PyTorch Lightning Implementations of Recent Satellite Image Classification !
Home-page: https://github.com/canturan10/satellighte
Author: Oguzcan Turan
Author-email: can.turan.10@gmail.com
License: MIT License
Classifier: Topic :: Scientific/Engineering :: Artificial Intelligence
Classifier: License :: OSI Approved :: MIT License
Classifier: Operating System :: OS Independent
Classifier: Programming Language :: Python :: 3
Classifier: Programming Language :: Python :: 3.8
Classifier: Programming Language :: Python :: 3.9
Requires-Python: >=3.8
License-File: LICENSE
Requires-Dist: fire (~=0.5.0)
Requires-Dist: imageio (~=2.30.0)
Requires-Dist: numpy (~=1.24.3)
Requires-Dist: pytorch-lightning (~=1.8.0)
Requires-Dist: PyYAML (~=6.0)
Requires-Dist: rich (~=13.3.5)
Requires-Dist: scikit-learn (~=1.2.2)
Requires-Dist: setuptools (==67.8.0)
Requires-Dist: torch (~=1.13.1)
Requires-Dist: torchmetrics (~=0.9.3)
Requires-Dist: torchvision (~=0.14.1)
Requires-Dist: uniplot (~=0.10.0)
Provides-Extra: all
Requires-Dist: fire (~=0.5.0) ; extra == 'all'
Requires-Dist: imageio (~=2.30.0) ; extra == 'all'
Requires-Dist: numpy (~=1.24.3) ; extra == 'all'
Requires-Dist: pytorch-lightning (~=1.8.0) ; extra == 'all'
Requires-Dist: PyYAML (~=6.0) ; extra == 'all'
Requires-Dist: rich (~=13.3.5) ; extra == 'all'
Requires-Dist: scikit-learn (~=1.2.2) ; extra == 'all'
Requires-Dist: setuptools (==67.8.0) ; extra == 'all'
Requires-Dist: torch (~=1.13.1) ; extra == 'all'
Requires-Dist: torchmetrics (~=0.9.3) ; extra == 'all'
Requires-Dist: torchvision (~=0.14.1) ; extra == 'all'
Requires-Dist: uniplot (~=0.10.0) ; extra == 'all'
Requires-Dist: pytest (>=6.0.0) ; extra == 'all'
Requires-Dist: pytest-pylint ; extra == 'all'
Requires-Dist: pytest-cov ; extra == 'all'
Requires-Dist: pylint ; extra == 'all'
Requires-Dist: black ; extra == 'all'
Provides-Extra: deploy
Requires-Dist: fire (~=0.5.0) ; extra == 'deploy'
Requires-Dist: imageio (~=2.30.0) ; extra == 'deploy'
Requires-Dist: numpy (~=1.24.3) ; extra == 'deploy'
Requires-Dist: pytorch-lightning (~=1.8.0) ; extra == 'deploy'
Requires-Dist: PyYAML (~=6.0) ; extra == 'deploy'
Requires-Dist: rich (~=13.3.5) ; extra == 'deploy'
Requires-Dist: scikit-learn (~=1.2.2) ; extra == 'deploy'
Requires-Dist: setuptools (==67.8.0) ; extra == 'deploy'
Requires-Dist: torch (~=1.13.1) ; extra == 'deploy'
Requires-Dist: torchmetrics (~=0.9.3) ; extra == 'deploy'
Requires-Dist: torchvision (~=0.14.1) ; extra == 'deploy'
Requires-Dist: uniplot (~=0.10.0) ; extra == 'deploy'
Requires-Dist: pytest (>=6.0.0) ; extra == 'deploy'
Requires-Dist: pytest-pylint ; extra == 'deploy'
Requires-Dist: pytest-cov ; extra == 'deploy'
Requires-Dist: pylint ; extra == 'deploy'
Requires-Dist: black ; extra == 'deploy'
Provides-Extra: docs
Requires-Dist: sphinxemoji ; extra == 'docs'
Requires-Dist: sphinx-rtd-theme ; extra == 'docs'
Requires-Dist: recommonmark ; extra == 'docs'
Requires-Dist: sphinx-markdown-tables ; extra == 'docs'
Requires-Dist: sphinxcontrib-napoleon ; extra == 'docs'
Requires-Dist: sphinx-autodoc-typehints ; extra == 'docs'
Requires-Dist: nbsphinx ; extra == 'docs'
Requires-Dist: furo ; extra == 'docs'
Provides-Extra: test
Requires-Dist: pytest (>=6.0.0) ; extra == 'test'
Requires-Dist: pytest-pylint ; extra == 'test'
Requires-Dist: pytest-cov ; extra == 'test'
Requires-Dist: pylint ; extra == 'test'
Requires-Dist: black ; extra == 'test'
